carbonaware_prefect/__init__.py
carbonaware_prefect/decorator.py
carbonaware_prefect/delay.py
carbonaware_prefect/introspection.py
carbonaware_prefect/task.py
carbonaware_prefect/examples/basic_decorator.py
carbonaware_prefect/examples/basic_task.py
carbonaware_prefect-0.1.3.dist-info/licenses/LICENSE
carbonaware_prefect-0.1.3.dist-info/METADATA
carbonaware_prefect-0.1.3.dist-info/WHEEL
carbonaware_prefect-0.1.3.dist-info/top_level.txt
carbonaware_prefect-0.1.3.dist-info/RECORD
