Metadata-Version: 2.4
Name: carbonaware-prefect
Version: 0.1.3
Summary: CarbonAware integration for Prefect
Requires-Python: >=3.10
License-File: LICENSE
Requires-Dist: carbonaware-scheduler-client>=1.0.0
Requires-Dist: httpx>=0.28.1
Requires-Dist: isodate>=0.7.2
Requires-Dist: tqdm>=4.67.1
Dynamic: license-file
